__init__.py
lsdensities/GPHLT_class.py
lsdensities/GP_class.py
lsdensities/HLT_class.py
lsdensities/InverseProblemWrapper.py
lsdensities/__init__.py
lsdensities/abw.py
lsdensities/core.py
lsdensities/plotutils.py
lsdensities/transform.py
lsdensities/correlator/__init__.py
lsdensities/correlator/correlatorUtils.py
lsdensities/correlator/fold.py
lsdensities/correlator/resample.py
lsdensities/utils/__init__.py
lsdensities/utils/rhoMath.py
lsdensities/utils/rhoParallelUtils.py
lsdensities/utils/rhoParser.py
lsdensities/utils/rhoStat.py
lsdensities/utils/rhoUtils.py
lsdensities-0.0.3.dist-info/licenses/LICENSE.txt
lsdensities-0.0.3.dist-info/METADATA
lsdensities-0.0.3.dist-info/WHEEL
lsdensities-0.0.3.dist-info/top_level.txt
lsdensities-0.0.3.dist-info/RECORD
