Metadata-Version: 2.4
Name: lsdensities
Version: 0.0.3
Summary: lsdensities: Lattice spectral densities
Author-email: Alessandro Lupo <alessandro.lupo@cpt.univ-mrs.fr>, Niccolo' Forzano <2227764@swansea.ac.uk>
Project-URL: Homepage, https://github.com/LupoA/lsdensities
Project-URL: Issues, https://github.com/LupoA/lsdensities/issues/
Classifier: Programming Language :: Python :: 3
Classifier: License :: OSI Approved :: MIT License
Classifier: Operating System :: OS Independent
Requires-Python: >=3.8
License-File: LICENSE.txt
Requires-Dist: numpy
Requires-Dist: mpmath
Requires-Dist: scipy
Requires-Dist: matplotlib
Requires-Dist: progressbar
Dynamic: license-file
